stefuna/__init__.py
stefuna/server.py
stefuna/stefuna.py
stefuna/util.py
stefuna/worker.py
stefuna-1.0.1.dist-info/AUTHORS.rst
stefuna-1.0.1.dist-info/LICENSE
stefuna-1.0.1.dist-info/METADATA
stefuna-1.0.1.dist-info/WHEEL
stefuna-1.0.1.dist-info/entry_points.txt
stefuna-1.0.1.dist-info/top_level.txt
stefuna-1.0.1.dist-info/RECORD
