Metadata-Version: 2.1
Name: stefuna
Version: 1.0.1
Summary: AWS Step Function Activity server framework
Home-page: https://github.com/irothschild/stefuna
Author: Ivo Rothschild
Author-email: ivo@clarify.io
License: MIT
Keywords: AWS Step Functions Activity task server worker
Platform: UNKNOWN
Classifier: Development Status :: 4 - Beta
Classifier: Intended Audience :: Developers
Classifier: License :: OSI Approved :: MIT License
Classifier: Natural Language :: English
Classifier: Programming Language :: Python :: 3
Requires-Python: >=3.4.0
Requires-Dist: boto3 (<2.0.0,>=1.4.6)
